PPOCRLabel/PPOCRLabel.py
PPOCRLabel/README.md
PPOCRLabel/__init__.py
PPOCRLabel/gen_ocr_train_val_test.py
PPOCRLabel/setup.cfg
PPOCRLabel/PPOCRLabel_Japan.egg-info/PKG-INFO
PPOCRLabel/PPOCRLabel_Japan.egg-info/SOURCES.txt
PPOCRLabel/PPOCRLabel_Japan.egg-info/dependency_links.txt
PPOCRLabel/PPOCRLabel_Japan.egg-info/entry_points.txt
PPOCRLabel/PPOCRLabel_Japan.egg-info/requires.txt
PPOCRLabel/PPOCRLabel_Japan.egg-info/top_level.txt
PPOCRLabel/libs/__init__.py
PPOCRLabel/libs/autoDialog.py
PPOCRLabel/libs/canvas.py
PPOCRLabel/libs/colorDialog.py
PPOCRLabel/libs/constants.py
PPOCRLabel/libs/create_ml_io.py
PPOCRLabel/libs/editinlist.py
PPOCRLabel/libs/hashableQListWidgetItem.py
PPOCRLabel/libs/keyDialog.py
PPOCRLabel/libs/labelColor.py
PPOCRLabel/libs/labelDialog.py
PPOCRLabel/libs/resources.py
PPOCRLabel/libs/settings.py
PPOCRLabel/libs/shape.py
PPOCRLabel/libs/stringBundle.py
PPOCRLabel/libs/toolBar.py
PPOCRLabel/libs/unique_label_qlist_widget.py
PPOCRLabel/libs/ustr.py
PPOCRLabel/libs/utils.py
PPOCRLabel/libs/zoomWidget.py
PPOCRLabel/resources/icons/Auto.png
PPOCRLabel/resources/icons/app.icns
PPOCRLabel/resources/icons/app.png
PPOCRLabel/resources/icons/app.svg
PPOCRLabel/resources/icons/cancel.png
PPOCRLabel/resources/icons/close.png
PPOCRLabel/resources/icons/color.png
PPOCRLabel/resources/icons/color_line.png
PPOCRLabel/resources/icons/copy.png
PPOCRLabel/resources/icons/delete.png
PPOCRLabel/resources/icons/done.png
PPOCRLabel/resources/icons/done.svg
PPOCRLabel/resources/icons/edit.png
PPOCRLabel/resources/icons/expert1.png
PPOCRLabel/resources/icons/expert2.png
PPOCRLabel/resources/icons/eye.png
PPOCRLabel/resources/icons/feBlend-icon.png
PPOCRLabel/resources/icons/file.png
PPOCRLabel/resources/icons/fit-width.png
PPOCRLabel/resources/icons/fit-window.png
PPOCRLabel/resources/icons/fit.png
PPOCRLabel/resources/icons/format_createml.png
PPOCRLabel/resources/icons/format_voc.png
PPOCRLabel/resources/icons/format_yolo.png
PPOCRLabel/resources/icons/help.png
PPOCRLabel/resources/icons/labels.png
PPOCRLabel/resources/icons/labels.svg
PPOCRLabel/resources/icons/lock.png
PPOCRLabel/resources/icons/new.png
PPOCRLabel/resources/icons/next.png
PPOCRLabel/resources/icons/objects.png
PPOCRLabel/resources/icons/open.png
PPOCRLabel/resources/icons/open.svg
ppocrlabel_japan-0.0.2.dist-info/METADATA
ppocrlabel_japan-0.0.2.dist-info/WHEEL
ppocrlabel_japan-0.0.2.dist-info/entry_points.txt
ppocrlabel_japan-0.0.2.dist-info/top_level.txt
ppocrlabel_japan-0.0.2.dist-info/RECORD
