Metadata-Version: 2.1
Name: ppocrlabel-japan
Version: 0.0.2
Summary: PPOCRLabelv2 is a semi-automatic graphic annotation tool suitable for OCR field, with built-in PP-OCR model to automatically detect and re-recognize data. It is written in Python3 and PyQT5, supporting rectangular box, table, irregular text and key information annotation modes. Annotations can be directly used for the training of PP-OCR detection and recognition models.
Home-page: https://github.com/PaddlePaddle/PaddleOCR
License: Apache License 2.0
Download-URL: https://github.com/PaddlePaddle/PaddleOCR.git
Keywords: ocr textdetection textrecognition paddleocr crnn east star-net rosetta ocrlite db chineseocr chinesetextdetection chinesetextrecognition
Platform: UNKNOWN
Classifier: Intended Audience :: Developers
Classifier: Operating System :: OS Independent
Classifier: Natural Language :: English
Classifier: Programming Language :: Python :: 3.6
Classifier: Programming Language :: Python :: 3.7
Classifier: Topic :: Utilities
Requires-Dist: pyqt5
Requires-Dist: paddleocr
Requires-Dist: xlrd (==1.2.0)
Requires-Dist: tqdm
